nmlread/__init__.py
nmlread-0.1.5.dist-info/LICENSE
nmlread-0.1.5.dist-info/METADATA
nmlread-0.1.5.dist-info/WHEEL
nmlread-0.1.5.dist-info/entry_points.txt
nmlread-0.1.5.dist-info/top_level.txt
nmlread-0.1.5.dist-info/RECORD
