Metadata-Version: 2.1
Name: nmlread
Version: 0.1.5
Summary: Microapp Fortran namelist reader
Home-page: UNKNOWN
Author: Youngsung Kim
Author-email: youngsung.kim.act2@gmail.com
License: UNKNOWN
Project-URL: Bug Reports, https://github.com/grnydawn/micro-nmlread/issues
Project-URL: Source, https://github.com/grnydawn/micro-nmlread
Keywords: microapp nmlread
Platform: UNKNOWN
Classifier: Development Status :: 3 - Alpha
Classifier: Intended Audience :: Science/Research
Classifier: Topic :: Scientific/Engineering
Classifier: License :: OSI Approved :: MIT License
Classifier: Programming Language :: Python :: 3
Classifier: Programming Language :: Python :: 3.5
Classifier: Programming Language :: Python :: 3.6
Classifier: Programming Language :: Python :: 3.7
Classifier: Programming Language :: Python :: 3.8
Requires-Dist: f90nml
Requires-Dist: microapp (>=0.2.3)
